esm_util/__init__.py
esm_util/esm_util.py
esm_util-0.1.8.dist-info/LICENSE
esm_util-0.1.8.dist-info/METADATA
esm_util-0.1.8.dist-info/WHEEL
esm_util-0.1.8.dist-info/top_level.txt
esm_util-0.1.8.dist-info/RECORD
